colititato/__init__.py
colititato/cli.py
tests/__init__.py
tests/test_game.py
colititato-0.1.1.dist-info/LICENSE
colititato-0.1.1.dist-info/METADATA
colititato-0.1.1.dist-info/WHEEL
colititato-0.1.1.dist-info/entry_points.txt
colititato-0.1.1.dist-info/top_level.txt
colititato-0.1.1.dist-info/RECORD
