Metadata-Version: 2.1
Name: colititato
Version: 0.1.1
Summary: A CLI implementation of the classic Tic Tac Toe game
Home-page: https://github.com/tiakas/colititato
Author: Giannis Tiakas
Author-email: giannis@tiakas.com
Keywords: cli,tic-tat-toe,game
Classifier: Development Status :: 3 - Alpha
Classifier: Intended Audience :: End Users/Desktop
Classifier: Topic :: Games/Entertainment :: Board Games
Classifier: License :: OSI Approved :: MIT License
Classifier: Programming Language :: Python :: 3
Requires-Python: >=3.6
License-File: LICENSE
